spiralflow/__init__.py
spiralflow/chat_history.py
spiralflow/chat_llm.py
spiralflow/chunking.py
spiralflow/flow.py
spiralflow/loading.py
spiralflow/memory.py
spiralflow/message.py
spiralflow/tools.py
spiralflow-0.0.6.dist-info/LICENSE
spiralflow-0.0.6.dist-info/METADATA
spiralflow-0.0.6.dist-info/WHEEL
spiralflow-0.0.6.dist-info/top_level.txt
spiralflow-0.0.6.dist-info/RECORD
