Metadata-Version: 2.1
Name: spiralflow
Version: 0.0.6
Summary: A framework for creating chat spirals for Large Language Models finetuned for conversations. Currently work-in-progress.
Home-page: https://github.com/Tiger767/Spiralflow
Author: Travis Hammond
License: MIT License
Classifier: Programming Language :: Python :: 3.9
Classifier: License :: OSI Approved :: MIT License
Classifier: Operating System :: OS Independent
Requires-Python: >=3.9
License-File: LICENSE
Requires-Dist: regex
Requires-Dist: openai
Requires-Dist: pandas
Requires-Dist: tiktoken
Requires-Dist: pymupdf
Requires-Dist: bs4
